fustor_fusion_sdk/__init__.py
fustor_fusion_sdk/client.py
fustor_fusion_sdk/interfaces.py
fustor_fusion_sdk-0.2.16.dist-info/METADATA
fustor_fusion_sdk-0.2.16.dist-info/WHEEL
fustor_fusion_sdk-0.2.16.dist-info/top_level.txt
fustor_fusion_sdk-0.2.16.dist-info/RECORD
