Metadata-Version: 2.4
Name: fustor-fusion-sdk
Version: 0.2.16
Summary: SDK for Fustor Fusion service
License-Expression: MIT
Requires-Dist: fustor-common
Requires-Dist: fustor-registry-client
